BaseColor/__init__.py
BaseColor/base_colors.py
basecolors-0.1.2.dist-info/LICENSE
basecolors-0.1.2.dist-info/METADATA
basecolors-0.1.2.dist-info/WHEEL
basecolors-0.1.2.dist-info/entry_points.txt
basecolors-0.1.2.dist-info/top_level.txt
basecolors-0.1.2.dist-info/RECORD
