Metadata-Version: 2.1
Name: basecolors
Version: 0.1.2
Summary: 在终端显示基本的文本颜色
Home-page: https://github.com/ga1008/basecolors
Author: Guardian
Author-email: zhling2012@live.com
Maintainer: Guardian
Maintainer-email: zhling2012@live.com
Classifier: Programming Language :: Python :: 3
Classifier: License :: OSI Approved :: MIT License
Classifier: Operating System :: OS Independent
License-File: LICENSE
